redislens/__init__.py
redislens/api.py
redislens/cli.py
redislens/redis_client.py
redislens/version.py
redislens/static/apple-touch-icon.png
redislens/static/asset-manifest.json
redislens/static/favicon-16x16.png
redislens/static/favicon-32x32.png
redislens/static/favicon.ico
redislens/static/index.html
redislens/static/logo192.png
redislens/static/logo512.png
redislens/static/manifest.json
redislens/static/robots.txt
redislens/static/site.webmanifest
redislens/static/assets/.DS_Store
redislens/static/assets/fontawesome/css/all.min.css
redislens/static/assets/fontawesome/webfonts/fa-brands-400.woff2
redislens/static/assets/fontawesome/webfonts/fa-regular-400.woff2
redislens/static/assets/fontawesome/webfonts/fa-solid-900.woff2
redislens/static/assets/js/tailwind.min.js
redislens/static/static/css/main.e6c13ad2.css
redislens/static/static/css/main.e6c13ad2.css.map
redislens/static/static/js/453.258b012d.chunk.js
redislens/static/static/js/453.258b012d.chunk.js.map
redislens/static/static/js/main.2131ad26.js
redislens/static/static/js/main.2131ad26.js.LICENSE.txt
redislens/static/static/js/main.2131ad26.js.map
redislens-1.0.0.dist-info/METADATA
redislens-1.0.0.dist-info/WHEEL
redislens-1.0.0.dist-info/entry_points.txt
redislens-1.0.0.dist-info/top_level.txt
redislens-1.0.0.dist-info/RECORD
